django_minio_storage-0.5.8.dist-info/licenses/LICENSE
django_minio_storage-0.5.8.dist-info/licenses/LICENSE-APACHE
minio_storage/__init__.py
minio_storage/apps.py
minio_storage/errors.py
minio_storage/files.py
minio_storage/policy.py
minio_storage/py.typed
minio_storage/storage.py
minio_storage/version.py
minio_storage/management/__init__.py
minio_storage/management/commands/__init__.py
minio_storage/management/commands/minio.py
django_minio_storage-0.5.8.dist-info/METADATA
django_minio_storage-0.5.8.dist-info/WHEEL
django_minio_storage-0.5.8.dist-info/top_level.txt
django_minio_storage-0.5.8.dist-info/RECORD
