Metadata-Version: 2.4
Name: django-minio-storage
Version: 0.5.8
Summary: Django file storage using the minio python client
Author-email: Thomas Frössman <thomasf@jossystem.se>, Tom Houlé <tom@kafunsho.be>
Maintainer-email: Thomas Frössman <thomasf@jossystem.se>
License-Expression: MIT OR Apache-2.0
Project-URL: Homepage, https://github.com/py-pa/django-minio-storage
Project-URL: Repository, https://github.com/py-pa/django-minio-storage
Project-URL: Documentation, https://django-minio-storage.readthedocs.io/
Classifier: Development Status :: 4 - Beta
Classifier: Environment :: Web Environment
Classifier: Intended Audience :: Developers
Classifier: Operating System :: OS Independent
Classifier: Programming Language :: Python
Classifier: Programming Language :: Python :: 3
Classifier: Framework :: Django
Requires-Python: >=3.9
License-File: LICENSE
License-File: LICENSE-APACHE
Requires-Dist: django>=4.2
Requires-Dist: minio>=7.1.16
Dynamic: license-file
